cli/__init__.py
cli/cli.py
cli/config.py
cli/image.py
cli/fonts/Prima Sans Bold.otf
cli/fonts/__init__.py
install/__init__.py
install/config.py
install/fix_install.py
jellyfin_tools-1.0.2.dist-info/LICENSE.txt
jellyfin_tools-1.0.2.dist-info/METADATA
jellyfin_tools-1.0.2.dist-info/WHEEL
jellyfin_tools-1.0.2.dist-info/entry_points.txt
jellyfin_tools-1.0.2.dist-info/top_level.txt
jellyfin_tools-1.0.2.dist-info/RECORD
