Metadata-Version: 2.1
Name: jellyfin-tools
Version: 1.0.2
Summary: Scripted tools for helping manage a Jellyfin library.
Home-page: https://github.com/eebette/Jellyfin-Tools
Author: Eric Bette
Author-email: eric.bette@pm.me
License: LICENSE.txt
License-File: LICENSE.txt
Requires-Dist: setuptools
Requires-Dist: numpy
Requires-Dist: Pillow
Requires-Dist: fonttools
Requires-Dist: opencv-contrib-python
